linkminer/__init__.py
linkminer/cli.py
linkminer/config.py
linkminer/crawler.py
linkminer/downloader.py
linkminer/kdownloader.py
linkminer/tempMan.py
linkminer/utils.py
linkminer-1.0.0.dist-info/licenses/LICENSE
linkminer-1.0.0.dist-info/METADATA
linkminer-1.0.0.dist-info/WHEEL
linkminer-1.0.0.dist-info/entry_points.txt
linkminer-1.0.0.dist-info/top_level.txt
linkminer-1.0.0.dist-info/RECORD
