Metadata-Version: 2.4
Name: linkminer
Version: 1.0.0
Summary: A CLI tool to recursively download specific file types from websites (e.g., pdf, txt.
Home-page: https://github.com/skye-cyber/linkminer
Author: Skye Wambua
Author-email: Skye <swskye17@gmail.com>
License:                     GNU GENERAL PUBLIC LICENSE
Keywords: crawler,downloader,web,search engine,automation
Classifier: Programming Language :: Python :: 3
Classifier: Environment :: Console
Classifier: Topic :: Utilities
Classifier: License :: OSI Approved :: GNU General Public License v3 (GPLv3)
Classifier: Operating System :: OS Independent
Requires-Python: >=3.7
License-File: LICENSE
Dynamic: author
Dynamic: home-page
Dynamic: license-file
Dynamic: requires-python
